odoo/addons/product_account_multicompany_default/README.rst
odoo/addons/product_account_multicompany_default/__init__.py
odoo/addons/product_account_multicompany_default/__manifest__.py
odoo/addons/product_account_multicompany_default/i18n/.empty
odoo/addons/product_account_multicompany_default/i18n/es.po
odoo/addons/product_account_multicompany_default/i18n/it.po
odoo/addons/product_account_multicompany_default/i18n/product_account_multicompany_default.pot
odoo/addons/product_account_multicompany_default/models/__init__.py
odoo/addons/product_account_multicompany_default/models/product.py
odoo/addons/product_account_multicompany_default/models/product_category.py
odoo/addons/product_account_multicompany_default/readme/CONFIGURE.rst
odoo/addons/product_account_multicompany_default/readme/CONTRIBUTORS.rst
odoo/addons/product_account_multicompany_default/readme/DESCRIPTION.rst
odoo/addons/product_account_multicompany_default/readme/ROADMAP.rst
odoo/addons/product_account_multicompany_default/readme/USAGE.rst
odoo/addons/product_account_multicompany_default/static/description/icon.png
odoo/addons/product_account_multicompany_default/static/description/index.html
odoo/addons/product_account_multicompany_default/static/description/wizard-mockup.drawio.png
odoo/addons/product_account_multicompany_default/tests/__init__.py
odoo/addons/product_account_multicompany_default/tests/test_product.py
odoo/addons/product_account_multicompany_default/tests/test_product_category.py
odoo/addons/product_account_multicompany_default/views/product_category_view.xml
odoo/addons/product_account_multicompany_default/views/product_template_view.xml
odoo_addon_product_account_multicompany_default-16.0.0.2.0.2.dist-info/METADATA
odoo_addon_product_account_multicompany_default-16.0.0.2.0.2.dist-info/WHEEL
odoo_addon_product_account_multicompany_default-16.0.0.2.0.2.dist-info/top_level.txt
odoo_addon_product_account_multicompany_default-16.0.0.2.0.2.dist-info/RECORD
