Metadata-Version: 2.1
Name: odoo-addon-product_account_multicompany_default
Version: 16.0.0.2.0.2
Summary: Set a default account for all companies of a product
Home-page: https://github.com/OCA/multi-company
Author: Moduon, Odoo Community Association (OCA)
Author-email: support@odoo-community.org
License: LGPL-3
Classifier: Programming Language :: Python
Classifier: Framework :: Odoo
Classifier: Framework :: Odoo :: 16.0
Classifier: License :: OSI Approved :: GNU Lesser General Public License v3 (LGPLv3)
Classifier: Development Status :: 3 - Alpha
Requires-Python: >=3.10
Requires-Dist: odoo<16.1dev,>=16.0a
